{
    "version": "https://jsonfeed.org/version/1",
    "title": "La isla de las tentaciones",
    "description": "",
    "home_page_url": "https://islatentaciones.ml",
    "feed_url": "https://islatentaciones.ml/feed.json",
    "user_comment": "",
    "author": {
        "name": "islatentaciones"
    },
    "items": [
        {
            "id": "https://islatentaciones.ml/3x06.html",
            "url": "https://islatentaciones.ml/3x06.html",
            "title": "Programa 6",
            "summary": " Llegan las terceras hogueras para ellos y para ellas y Diego pide por primera vez en esta edición una&hellip;",
            "content_html": "<p> </p>\n<p>Llegan las terceras hogueras para ellos y para ellas y Diego pide por primera vez en esta edición una hoguera de confrontación con Lola. Si su pareja no lo acepta, él deberá abandonar el programa inmediatamente.</p>\n<p> </p>\n<p class=\"msg msg--info\">DEBIDO A UNA SOLICITUD DE MEDIASET ESTA PAGINA WEB ESTARA CERRADA A LAS 22:00, SIGUENOS EN INSTAGRAM PARA ENCONTRARNOS, <span style=\"text-decoration: underline; color: #ba372a;\"><strong><a href=\"https://www.instagram.com/islatentaciones.ml/\">CLICK AQUI</a></strong></span></p>\n<div class=\"post__iframe\"><iframe loading=\"lazy\" width=\"560\" height=\"315\" src=\"//ok.ru/videoembed/2957551602236\" frameborder=\"0\" allow=\"autoplay\" allowfullscreen=\"allowfullscreen\"></iframe></div>",
            "image": "https://islatentaciones.ml/media/posts/14/Q5EAiGd.png",
            "author": {
                "name": "islatentaciones"
            },
            "tags": [
                   "Temporada 3",
                   "Programas"
            ],
            "date_published": "2021-02-24T19:25:19+00:00",
            "date_modified": "2021-02-26T14:18:09+00:00"
        }
    ]
}
